{
  "kind": "singleType",
  "collectionName": "not_founds",
  "info": {
    "singularName": "not-found",
    "pluralName": "not-founds",
    "displayName": "Not Found",
    "description": ""
  },
  "options": {
    "draftAndPublish": true
  },
  "pluginOptions": {},
  "attributes": {
    "title": {
      "type": "string"
    },
    "description": {
      "type": "text"
    },
    "image": {
      "type": "component",
      "repeatable": false,
      "component": "shared.media"
    },
    "link": {
      "type": "component",
      "repeatable": false,
      "component": "navigation.link"
    },
    "seo": {
      "type": "component",
      "repeatable": false,
      "component": "shared.seo"
    }
  }
}
